README.md
setup.cfg
setup.py
sqs_workflow/__init__.py
sqs_workflow.egg-info/PKG-INFO
sqs_workflow.egg-info/SOURCES.txt
sqs_workflow.egg-info/dependency_links.txt
sqs_workflow.egg-info/not-zip-safe
sqs_workflow.egg-info/top_level.txt