Metadata-Version: 1.0
Name: sqs-workflow
Version: 0.1
Summary: Here is will be a better description soon
Home-page: https://github.com/alexkoz/sqs_workflow
Author: Alex Kozlov
Author-email: alex.d.kozlov@gmail.com
License: UNKNOWN
Platform: UNKNOWN
